synodrivekit/__init__.py
synodrivekit/drive_tool/__init__.py
synodrivekit/drive_tool/drive_tool.py
synodrivekit-1.4.3.dist-info/METADATA
synodrivekit-1.4.3.dist-info/WHEEL
synodrivekit-1.4.3.dist-info/top_level.txt
synodrivekit-1.4.3.dist-info/RECORD
