Metadata-Version: 2.1
Name: synodrivekit
Version: 1.4.3
Summary: Библиотека для работы с таблицами synology
Home-page: UNKNOWN
License: UNKNOWN
Platform: UNKNOWN
Requires-Dist: pandas
Requires-Dist: openpyxl
Requires-Dist: numpy
